odoo/addons/l10n_ch_qriban/README.rst
odoo/addons/l10n_ch_qriban/__init__.py
odoo/addons/l10n_ch_qriban/__manifest__.py
odoo/addons/l10n_ch_qriban/i18n/l10n_ch_qriban.pot
odoo/addons/l10n_ch_qriban/models/__init__.py
odoo/addons/l10n_ch_qriban/models/invoice.py
odoo/addons/l10n_ch_qriban/models/res_bank.py
odoo/addons/l10n_ch_qriban/readme/DESCRIPTION.rst
odoo/addons/l10n_ch_qriban/static/description/icon.png
odoo/addons/l10n_ch_qriban/static/description/index.html
odoo/addons/l10n_ch_qriban/tests/__init__.py
odoo/addons/l10n_ch_qriban/tests/test_swissqr.py
odoo/addons/l10n_ch_qriban/views/res_bank_views.xml
odoo/addons/l10n_ch_qriban/views/swissqr_report.xml
odoo12_addon_l10n_ch_qriban-12.0.0.1.0.99.dev6.dist-info/METADATA
odoo12_addon_l10n_ch_qriban-12.0.0.1.0.99.dev6.dist-info/WHEEL
odoo12_addon_l10n_ch_qriban-12.0.0.1.0.99.dev6.dist-info/top_level.txt
odoo12_addon_l10n_ch_qriban-12.0.0.1.0.99.dev6.dist-info/RECORD
