Metadata-Version: 2.1
Name: odoo12-addon-l10n-ch-qriban
Version: 12.0.0.1.0.99.dev6
Summary: Switzerland - QR-IBAN
Home-page: UNKNOWN
Author: Odoo S.A, Camptocamp, Odoo Community Association (OCA)
Author-email: support@odoo-community.org
License: LGPL-3
Platform: UNKNOWN
Classifier: Programming Language :: Python
Classifier: Framework :: Odoo
Classifier: Framework :: Odoo :: 12.0
Classifier: License :: OSI Approved :: GNU Lesser General Public License v3 (LGPLv3)
Requires-Python: >=3.5
Requires-Dist: odoo12-addon-l10n-ch-fix-isr-reference
Requires-Dist: odoo <12.1dev,>=12.0a
